silica/__init__.py
silica/_version.py
silica/cli.py
silica/cron/__init__.py
silica/cron/app.py
silica/cron/cli.py
silica/cron/scheduler.py
silica/cron/config/__init__.py
silica/cron/config/logging.py
silica/cron/config/settings.py
silica/cron/models/__init__.py
silica/cron/models/base.py
silica/cron/models/id_generator.py
silica/cron/models/prompt.py
silica/cron/routes/__init__.py
silica/cron/routes/dashboard.py
silica/cron/routes/jobs.py
silica/cron/routes/prompts.py
silica/cron/scripts/__init__.py
silica/cron/scripts/litestream_manager.py
silica/cron/static/.gitkeep
silica/cron/static/style.css
silica/cron/templates/base.html
silica/cron/templates/dashboard.html
silica/cron/templates/jobs.html
silica/cron/templates/prompts.html
silica/cron/templates/session_history.html
silica/developer/__init__.py
silica/developer/agent_loop.py
silica/developer/commit.py
silica/developer/compacter.py
silica/developer/compaction_validation.py
silica/developer/context.py
silica/developer/hdev.py
silica/developer/history.py
silica/developer/hybrid_interface.py
silica/developer/loop_detection.py
silica/developer/models.py
silica/developer/plans.py
silica/developer/prompt.py
silica/developer/rate_limiter.py
silica/developer/request_logger.py
silica/developer/sandbox.py
silica/developer/tool_result_limit.py
silica/developer/toolbox.py
silica/developer/user_interface.py
silica/developer/utils.py
silica/developer/cli/__init__.py
silica/developer/cli/history_sync.py
silica/developer/cli/memory_sync.py
silica/developer/cli/sync_helpers.py
silica/developer/island_client/__init__.py
silica/developer/island_client/client.py
silica/developer/island_client/exceptions.py
silica/developer/island_client/protocol.py
silica/developer/mcp/__init__.py
silica/developer/mcp/client.py
silica/developer/mcp/config.py
silica/developer/mcp/manager.py
silica/developer/mcp/schema.py
silica/developer/memory/__init__.py
silica/developer/memory/conflict_resolver.py
silica/developer/memory/exceptions.py
pysilica-0.7.9.dist-info/METADATA
pysilica-0.7.9.dist-info/WHEEL
pysilica-0.7.9.dist-info/entry_points.txt
pysilica-0.7.9.dist-info/top_level.txt
pysilica-0.7.9.dist-info/RECORD
