Metadata-Version: 2.4
Name: pysilica
Version: 0.7.9
Summary: A command line tool for creating workspaces for agents on top of piku
Author-email: Sean Fitzgerald <sean@fitzgeralds.me>
Classifier: Programming Language :: Python :: 3
Classifier: License :: OSI Approved :: MIT License
Classifier: Operating System :: OS Independent
Requires-Python: >=3.11
Requires-Dist: cyclopts>=2.0.0
Requires-Dist: rich>=13.3.0
Requires-Dist: requests>=2.28.0
Requires-Dist: pyyaml>=6.0
Requires-Dist: gitpython>=3.1.0
Requires-Dist: flask>=3.0.0
Requires-Dist: filelock>=3.13.1
Requires-Dist: dotenv>=0.9.9
Requires-Dist: anthropic>=0.62.0
Requires-Dist: pydantic>=2.11.7
Requires-Dist: aiofiles>=24.1.0
Requires-Dist: pathspec>=0.12.1
Requires-Dist: prompt-toolkit>=3.0.51
Requires-Dist: bs4>=0.0.2
Requires-Dist: markdownify>=1.2.0
Requires-Dist: brave-search-python-client>=0.4.27
Requires-Dist: google-api-python-client>=2.178.0
Requires-Dist: google-auth-oauthlib>=1.2.2
Requires-Dist: markdown>=3.8.2
Requires-Dist: fastapi>=0.116.1
Requires-Dist: sqlalchemy>=2.0.43
Requires-Dist: sqlalchemy-orm>=1.2.10
Requires-Dist: uvicorn>=0.35.0
Requires-Dist: croniter>=6.0.0
Requires-Dist: python-multipart>=0.0.20
Requires-Dist: pydantic-settings>=2.0.0
Requires-Dist: heare-ids>=0.1.3
Requires-Dist: psutil>=5.9.0
Requires-Dist: structlog>=24.0.0
Requires-Dist: setuptools-scm>=9.2.0
Requires-Dist: playwright>=1.40.0
Requires-Dist: boto3>=1.34.0
Requires-Dist: httpx>=0.27.0
Requires-Dist: opencv-python>=4.8.0
Requires-Dist: bashlex>=0.18
Requires-Dist: mcp>=1.0.0
Requires-Dist: keyring>=24.0.0
Provides-Extra: dev
Requires-Dist: pre-commit>=4.2.0; extra == "dev"
Requires-Dist: pytest>=8.3.5; extra == "dev"
Requires-Dist: pytest-asyncio>=1.1.0; extra == "dev"
Requires-Dist: pytest-cov>=6.0.0; extra == "dev"
Requires-Dist: ruff>=0.13.0; extra == "dev"
Requires-Dist: moto[s3]>=5.0.0; extra == "dev"
Requires-Dist: pytest-mock>=3.15.1; extra == "dev"
